tests/__init__.py
buildify_api-2.0.0.dist-info/LICENSE
buildify_api-2.0.0.dist-info/METADATA
buildify_api-2.0.0.dist-info/WHEEL
buildify_api-2.0.0.dist-info/entry_points.txt
buildify_api-2.0.0.dist-info/top_level.txt
buildify_api-2.0.0.dist-info/RECORD
