Metadata-Version: 2.2
Name: buildify-api
Version: 2.0.0
Summary: Buildify API is a Python library for real estate data processing.
Home-page: https://unrealos.com
Author: Unrealos
Author-email: m@unrealos.com
License: MIT
Project-URL: Company, https://unrealos.com
Project-URL: Source, https://github.com/markolofsen/buildify-api/
Project-URL: Tracker, https://github.com/markolofsen/buildify-api/issues
Keywords: buildify,real-estate,api,data-processing,python-library
Classifier: Development Status :: 4 - Beta
Classifier: Intended Audience :: Developers
Classifier: Topic :: Software Development :: Libraries :: Python Modules
Classifier: Topic :: Scientific/Engineering :: Information Analysis
Classifier: Topic :: Software Development :: Build Tools
Classifier: License :: OSI Approved :: MIT License
Classifier: Programming Language :: Python :: 3.7
Classifier: Programming Language :: Python :: 3.8
Classifier: Programming Language :: Python :: 3.9
Classifier: Programming Language :: Python :: 3.10
Classifier: Programming Language :: Python :: 3.11
Requires-Python: >=3.8
License-File: LICENSE
Requires-Dist: requests==2.32.3
Requires-Dist: python-slugify==8.0.4
Requires-Dist: python-dateutil==2.9.0.post0
Requires-Dist: dateparser==1.2.0
Provides-Extra: testing
Requires-Dist: pytest>=7.0; extra == "testing"
Requires-Dist: pytest-cov>=4.0; extra == "testing"
Requires-Dist: tox>=4.0; extra == "testing"
Requires-Dist: mypy>=1.0; extra == "testing"
Requires-Dist: flake8>=6.0; extra == "testing"
Provides-Extra: dev
Requires-Dist: black>=23.0; extra == "dev"
Requires-Dist: isort>=5.12; extra == "dev"
Requires-Dist: pre-commit>=3.0; extra == "dev"
